flask_tailwindcss/__init__.py
flask_tailwindcss/main.py
flask_tailwindcss-0.3.dist-info/METADATA
flask_tailwindcss-0.3.dist-info/WHEEL
flask_tailwindcss-0.3.dist-info/entry_points.txt
flask_tailwindcss-0.3.dist-info/top_level.txt
flask_tailwindcss-0.3.dist-info/RECORD
