Metadata-Version: 2.1
Name: flask-tailwindcss
Version: 0.3
Summary: Integrate TailwindCSS in one command.
Author: Etienne DTS
License: MIT
